django_img_optimizer/__init__.py
django_img_optimizer/apps.py
django_img_optimizer/utils.py
django_img_optimizer/management/__init__.py
django_img_optimizer/management/commands/__init__.py
django_img_optimizer/management/commands/optimize_images.py
django_img_optimizer/templatetags/image_optimizer.py
django_img_optimizer-1.5.dist-info/licenses/LICENSE
django_img_optimizer-1.5.dist-info/METADATA
django_img_optimizer-1.5.dist-info/WHEEL
django_img_optimizer-1.5.dist-info/top_level.txt
django_img_optimizer-1.5.dist-info/RECORD
