Metadata-Version: 2.4
Name: django-img-optimizer
Version: 1.5
Summary: Image optimizer for Django.
Author: Peter Stavrou
License: MIT
Project-URL: Homepage, https://github.com/peterstavrou/django-img-optimizer
Classifier: License :: OSI Approved :: MIT License
Requires-Python: >=3.8
License-File: LICENSE
Requires-Dist: pillow>=10.2.0
Dynamic: license-file
